characterization/__init__.py
characterization/run_feature_analysis.py
characterization/run_processor.py
characterization/run_scenario_viz.py
characterization/run_score_analysis.py
characterization/config/run_analysis.yaml
characterization/config/run_processor.yaml
characterization/config/characterizer/default.yaml
characterization/config/characterizer/individual_features.yaml
characterization/config/characterizer/individual_scores.yaml
characterization/config/characterizer/individual_scores_categorical.yaml
characterization/config/characterizer/interaction_features.yaml
characterization/config/characterizer/interaction_scores.yaml
characterization/config/characterizer/interaction_scores_categorical.yaml
characterization/config/characterizer/safeshift_features.yaml
characterization/config/characterizer/safeshift_scores.yaml
characterization/config/characterizer/safeshift_scores_categorical.yaml
characterization/config/dataset/waymo.yaml
characterization/config/debug/sequential.yaml
characterization/config/hydra/default.yaml
characterization/config/paths/default.yaml
characterization/config/paths/test.yaml
characterization/config/paths/waymo.yaml
characterization/config/viz/scenario.yaml
characterization/config/viz/scenario_animated.yaml
characterization/datasets/__init__.py
characterization/datasets/base_dataset.py
characterization/datasets/waymo.py
characterization/datasets/waymo_preprocess.py
characterization/examples/run_single_scenario.py
characterization/features/__init__.py
characterization/features/base_feature.py
characterization/features/individual_features.py
characterization/features/individual_utils.py
characterization/features/interaction_features.py
characterization/features/interaction_utils.py
characterization/features/safeshift_features.py
characterization/probing/__init__.py
characterization/processors/__init__.py
characterization/processors/base_processor.py
characterization/processors/feature_processor.py
scenario_characterization-0.3.2.dist-info/METADATA
scenario_characterization-0.3.2.dist-info/WHEEL
scenario_characterization-0.3.2.dist-info/licenses/LICENSE
scenario_characterization-0.3.2.dist-info/RECORD
