Metadata-Version: 2.4
Name: scenario-characterization
Version: 0.3.2
Summary: Automated Scenario Characterization Toolkit.
Project-URL: Homepage, https://navars.xyz/safeshift/
Project-URL: Repository, https://github.com/navarrs/ScenarioCharacterization
Author: Duan Yutong (dyt-stackav)
Author-email: Ingrid Navarro <ingridn@cmu.edu>, Alonso Cano <acanovil@cmu.edu>
License:                                  Apache License
License-File: LICENSE
Keywords: Characterization,Safety Metrics,Trajectory Datasets
Classifier: Development Status :: 2 - Pre-Alpha
Classifier: License :: OSI Approved :: Apache Software License
Classifier: Operating System :: POSIX :: Linux
Classifier: Programming Language :: Python
Classifier: Programming Language :: Python :: 3
Classifier: Programming Language :: Python :: 3.10
Classifier: Programming Language :: Python :: 3.12
Classifier: Programming Language :: Python :: 3.13
Requires-Python: <3.14,>=3.10
Requires-Dist: colorlog>=6.9.0
Requires-Dist: hydra-core>=1.3.2
Requires-Dist: joblib>=1.5.1
Requires-Dist: natsort>=8.4.0
Requires-Dist: numpy>=1.21.5
Requires-Dist: omegaconf>=2.3.0
Requires-Dist: pandas>=1.5.3
Requires-Dist: pydantic>=2.9.5
Requires-Dist: rich>=13.9.4
Requires-Dist: scipy>=1.9.1
Requires-Dist: seaborn>=0.12.0
Requires-Dist: shapely>=2.0.7
Requires-Dist: torch>=2.3.1
Requires-Dist: tqdm>=4.67.1
Provides-Extra: dev
Requires-Dist: pre-commit>=4.2.0; extra == 'dev'
Provides-Extra: viz
Requires-Dist: matplotlib>=3.6.1; extra == 'viz'
Requires-Dist: seaborn>=0.12.0; extra == 'viz'
Provides-Extra: waymo
Requires-Dist: tensorflow==2.11; (python_version == '3.10') and extra == 'waymo'
Requires-Dist: waymo-open-dataset-tf-2-11-0>=1.6.1; (python_version == '3.10') and extra == 'waymo'
